pygrex/__init__.py
pygrex/__main__.py
pygrex/config.py
pygrex/run.py
pygrex-1.0.2.dist-info/licenses/LICENSE.md
pygrex-1.0.2.dist-info/METADATA
pygrex-1.0.2.dist-info/WHEEL
pygrex-1.0.2.dist-info/top_level.txt
pygrex-1.0.2.dist-info/RECORD
