Metadata-Version: 2.4
Name: pygrex
Version: 1.0.2
Summary: A PYthon Group Recommender EXplainable Library
License: MIT License
Requires-Python: >=3.11
License-File: LICENSE.md
Requires-Dist: dash
Requires-Dist: dash-core-components
Requires-Dist: dash-html-components
Requires-Dist: implicit
Requires-Dist: jupyter-dash
Requires-Dist: matplotlib
Requires-Dist: mlxtend
Requires-Dist: networkx
Requires-Dist: numpy
Requires-Dist: pandas
Requires-Dist: plotly
Requires-Dist: python-box
Requires-Dist: scikit-learn
Requires-Dist: scipy
Requires-Dist: seaborn
Requires-Dist: torch
Requires-Dist: tqdm
Requires-Dist: streamlit
Requires-Dist: umap-learn
Requires-Dist: PyYAML
Provides-Extra: dev
Requires-Dist: pytest>=7.0.0; extra == "dev"
Requires-Dist: flake8>=4.0.0; extra == "dev"
Requires-Dist: black>=22.0.0; extra == "dev"
Requires-Dist: isort>=5.10.0; extra == "dev"
Requires-Dist: coverage; extra == "dev"
Requires-Dist: threadpoolctl; extra == "dev"
Dynamic: license-file
